{
  "command": "optimize",
  "config": {
    "b1_max": 500000.0,
    "b1_min": 1000.0,
    "b2_max": 5000000.0,
    "b2_min": 10000.0,
    "curve_timeout_sec": 4.0,
    "curves_per_n": 3,
    "method": "rs",
    "method_params": {
      "budget": 12
    },
    "ratio_max": 25.0,
    "seed": 11,
    "workers": 12
  },
  "dataset": "data/numbers/20_dset_20260329T133751Z/train.json",
  "dataset_target_digits": 20,
  "ecm_bin": "ecm",
  "optimization_trace": [
    {
      "b1": 83818,
      "b2": 2010180,
      "elapsed_sec": 0.22028326799772913,
      "eval": 1,
      "fitness": 1.1586432769654493,
      "kind": "evaluation",
      "timestamp_utc": "2026-03-29T13:38:24.644943+00:00"
    },
    {
      "b1": 83818,
      "b2": 2010180,
      "elapsed_sec": 0.22033441500389017,
      "eval": 1,
      "fitness": 1.1586432769654493,
      "kind": "new_best",
      "timestamp_utc": "2026-03-29T13:38:24.644988+00:00"
    },
    {
      "elapsed_sec": 0.22041363600146724,
      "eval": 1,
      "kind": "step",
      "message": "step=1/12 new_best b1=83819 b2=2010180 fitness=1.1586432769654493",
      "timestamp_utc": "2026-03-29T13:38:24.645067+00:00"
    },
    {
      "b1": 490720,
      "b2": 3145153,
      "elapsed_sec": 1.0302131030039163,
      "eval": 2,
      "fitness": 7.412439974978042,
      "kind": "evaluation",
      "timestamp_utc": "2026-03-29T13:38:25.454871+00:00"
    },
    {
      "b1": 8680,
      "b2": 216999,
      "elapsed_sec": 1.1114311929995893,
      "eval": 3,
      "fitness": 0.2558652375046222,
      "kind": "evaluation",
      "timestamp_utc": "2026-03-29T13:38:25.536089+00:00"
    },
    {
      "b1": 8680,
      "b2": 216999,
      "elapsed_sec": 1.1114888480005902,
      "eval": 3,
      "fitness": 0.2558652375046222,
      "kind": "new_best",
      "timestamp_utc": "2026-03-29T13:38:25.536142+00:00"
    },
    {
      "elapsed_sec": 1.1115675539986114,
      "eval": 3,
      "kind": "step",
      "message": "step=3/12 new_best b1=8680 b2=217000 fitness=0.2558652375046222",
      "timestamp_utc": "2026-03-29T13:38:25.536221+00:00"
    },
    {
      "b1": 15248,
      "b2": 94933,
      "elapsed_sec": 1.2020907230034936,
      "eval": 4,
      "fitness": 0.32152838255569804,
      "kind": "evaluation",
      "timestamp_utc": "2026-03-29T13:38:25.626750+00:00"
    },
    {
      "b1": 152618,
      "b2": 1609408,
      "elapsed_sec": 1.5301243389985757,
      "eval": 5,
      "fitness": 2.451326007485477,
      "kind": "evaluation",
      "timestamp_utc": "2026-03-29T13:38:25.954782+00:00"
    },
    {
      "b1": 1249,
      "b2": 31225,
      "elapsed_sec": 1.600852183997631,
      "eval": 6,
      "fitness": 0.13538258250264334,
      "kind": "evaluation",
      "timestamp_utc": "2026-03-29T13:38:26.025510+00:00"
    },
    {
      "b1": 1249,
      "b2": 31225,
      "elapsed_sec": 1.600905788000091,
      "eval": 6,
      "fitness": 0.13538258250264334,
      "kind": "new_best",
      "timestamp_utc": "2026-03-29T13:38:26.025558+00:00"
    },
    {
      "elapsed_sec": 1.600982395997562,
      "eval": 6,
      "kind": "step",
      "message": "step=6/12 new_best b1=1250 b2=31250 fitness=0.13538258250264334",
      "timestamp_utc": "2026-03-29T13:38:26.025636+00:00"
    },
    {
      "b1": 6168,
      "b2": 154199,
      "elapsed_sec": 1.684651854004187,
      "eval": 7,
      "fitness": 0.24202095499276766,
      "kind": "evaluation",
      "timestamp_utc": "2026-03-29T13:38:26.109310+00:00"
    },
    {
      "b1": 7265,
      "b2": 181625,
      "elapsed_sec": 1.7596718179993331,
      "eval": 8,
      "fitness": 0.22548767750777188,
      "kind": "evaluation",
      "timestamp_utc": "2026-03-29T13:38:26.184329+00:00"
    },
    {
      "b1": 32999,
      "b2": 75089,
      "elapsed_sec": 1.865014353999868,
      "eval": 9,
      "fitness": 0.5003084675081482,
      "kind": "evaluation",
      "timestamp_utc": "2026-03-29T13:38:26.289672+00:00"
    },
    {
      "b1": 7449,
      "b2": 186225,
      "elapsed_sec": 1.943468876001134,
      "eval": 10,
      "fitness": 0.23893658246379346,
      "kind": "evaluation",
      "timestamp_utc": "2026-03-29T13:38:26.368127+00:00"
    },
    {
      "b1": 5601,
      "b2": 140025,
      "elapsed_sec": 2.0222128579989658,
      "eval": 11,
      "fitness": 0.22274472004937707,
      "kind": "evaluation",
      "timestamp_utc": "2026-03-29T13:38:26.446871+00:00"
    },
    {
      "b1": 129451,
      "b2": 709863,
      "elapsed_sec": 2.275134199000604,
      "eval": 12,
      "fitness": 1.3789295305305131,
      "kind": "evaluation",
      "timestamp_utc": "2026-03-29T13:38:26.699792+00:00"
    }
  ],
  "optimized": {
    "b1": 1250,
    "b2": 31250,
    "method": "rs",
    "objective": 0.13538258250264334
  },
  "package_version": "0.1.0",
  "plots": {
    "b1_b2_trajectory": "data/experiments/20_dset_20260329T133751Z/rs/optimize_20260329T133826Z/plots/rs_optimize_20260329T133826Z_b1_b2_trajectory.png",
    "convergence": "data/experiments/20_dset_20260329T133751Z/rs/optimize_20260329T133826Z/plots/rs_optimize_20260329T133826Z_convergence.png",
    "jump_plot": "data/experiments/20_dset_20260329T133751Z/rs/optimize_20260329T133826Z/plots/rs_optimize_20260329T133826Z_jump_plot.png",
    "progress_by_phase": "data/experiments/20_dset_20260329T133751Z/rs/optimize_20260329T133826Z/plots/rs_optimize_20260329T133826Z_progress_by_phase.png",
    "raw_fitness": "data/experiments/20_dset_20260329T133751Z/rs/optimize_20260329T133826Z/plots/rs_optimize_20260329T133826Z_raw_fitness.png"
  },
  "run_stats": {
    "eval_per_sec": 5.274414144568364,
    "evaluation_count": 12,
    "improvement_percent": 88.31542156294923,
    "max_plateau_evals": 6,
    "new_best_count": 3,
    "time_to_best_sec": 1.600852183997631,
    "time_to_first_improvement_sec": 0.22033441500389017,
    "total_runtime_sec": 2.275134199000604
  },
  "suggested_baseline": {
    "b1": 2000,
    "b2": 40000,
    "source": "exact_table",
    "table_target_digits": 20
  },
  "timestamp_utc": "20260329T133827Z"
}
